hintedtext/__init__.py
hintedtext/hintedentry.py
hintedtext/hintedtext.py
hintedtext-0.6.0.dist-info/LICENSE.md
hintedtext-0.6.0.dist-info/WHEEL
hintedtext-0.6.0.dist-info/METADATA
hintedtext-0.6.0.dist-info/RECORD
