Metadata-Version: 2.1
Name: hintedtext
Version: 0.6.0
Summary: Tkinter Text widget with an extra hint attribute.
Home-page: https://github.com/billyeatcookies/hintedtext
License: MIT
Author: Billy
Author-email: billydevbusiness@gmail.com
Requires-Python: >=3.10,<4.0
Classifier: License :: OSI Approved :: MIT License
Classifier: Programming Language :: Python :: 3
Classifier: Programming Language :: Python :: 3.10
Project-URL: Repository, https://github.com/billyeatcookies/hintedtext
